contohku/__init__.py
contohku-0.1.0.dist-info/licenses/LICENSE
contohku-0.1.0.dist-info/METADATA
contohku-0.1.0.dist-info/WHEEL
contohku-0.1.0.dist-info/top_level.txt
contohku-0.1.0.dist-info/RECORD
