Metadata-Version: 2.4
Name: contohku
Version: 0.1.0
Summary: Contoh package Python buatan sendiri
Author-email: Nama Kamu <email@example.com>
License-Expression: MIT
Requires-Python: >=3.7
License-File: LICENSE
Dynamic: license-file
